ming_nndl-0.0.1.dist-info/licenses/LICENSE
nndl/__init__.py
nndl/activation.py
nndl/dataset.py
nndl/metric.py
nndl/op.py
nndl/optimizer.py
nndl/runner.py
nndl/tools.py
ming_nndl-0.0.1.dist-info/METADATA
ming_nndl-0.0.1.dist-info/WHEEL
ming_nndl-0.0.1.dist-info/top_level.txt
ming_nndl-0.0.1.dist-info/RECORD
