Metadata-Version: 2.4
Name: ming-nndl
Version: 0.0.1
Summary: Neural Network and Deep Learning (NNDL) library based on PaddlePaddle
Author-email: Ming <contact@example.com>
Project-URL: Homepage, https://github.com/lgnorant-lu/nndl
Project-URL: Bug Tracker, https://github.com/lgnorant-lu/nndl/issues
Project-URL: Repository, https://github.com/lgnorant-lu/nndl
Project-URL: PyPI, https://pypi.org/project/ming-nndl/
Classifier: Programming Language :: Python :: 3
Classifier: Programming Language :: Python :: 3.7
Classifier: Programming Language :: Python :: 3.8
Classifier: Programming Language :: Python :: 3.9
Classifier: Programming Language :: Python :: 3.10
Classifier: Programming Language :: Python :: 3.11
Classifier: License :: OSI Approved :: MIT License
Classifier: Operating System :: OS Independent
Classifier: Topic :: Scientific/Engineering :: Artificial Intelligence
Classifier: Topic :: Software Development :: Libraries :: Python Modules
Requires-Python: >=3.7
License-File: LICENSE
Requires-Dist: paddlepaddle>=2.0.0
Requires-Dist: numpy
Requires-Dist: matplotlib
Requires-Dist: pandas
Requires-Dist: Pillow
Dynamic: license-file
